iniparser2/__init__.py
iniparser2-3.0.0.dist-info/LICENSE
iniparser2-3.0.0.dist-info/METADATA
iniparser2-3.0.0.dist-info/WHEEL
iniparser2-3.0.0.dist-info/top_level.txt
iniparser2-3.0.0.dist-info/RECORD
