Metadata-Version: 2.1
Name: iniparser2
Version: 3.0.0
Summary: An INI parser or config parser
Home-page: https://github.com/HugeBrain16/iniparser2
Author: HugeBrain16
Author-email: joshtuck373@gmail.com
License: MIT
Keywords: iniparser configparser ini config parser file
Platform: UNKNOWN
Classifier: Development Status :: 5 - Production/Stable
Classifier: Intended Audience :: Developers
Classifier: License :: OSI Approved :: MIT License
Classifier: Programming Language :: Python :: 3
